AUTHORS.rst
CONTRIBUTING.rst
HISTORY.rst
LICENSE
MANIFEST.in
README.rst
setup.cfg
setup.py
cdk_expects_matcher/CdkMatchers.py
cdk_expects_matcher/__init__.py
cdk_expects_matcher/conftest.py
cdk_expects_matcher.egg-info/PKG-INFO
cdk_expects_matcher.egg-info/SOURCES.txt
cdk_expects_matcher.egg-info/dependency_links.txt
cdk_expects_matcher.egg-info/not-zip-safe
cdk_expects_matcher.egg-info/requires.txt
cdk_expects_matcher.egg-info/top_level.txt
cdk_expects_matcher/sample_cdk_app/__init__.py
cdk_expects_matcher/sample_cdk_app/cdk.py
docs/Makefile
docs/authors.rst
docs/conf.py
docs/contributing.rst
docs/history.rst
docs/index.rst
docs/installation.rst
docs/make.bat
docs/readme.rst
docs/usage.rst
tests/__init__.py
tests/test_cdk_expects_matcher.py