Metadata-Version: 1.2
Name: cdk-expects-matcher
Version: 0.1.2
Summary: Python package to provide a unit testing framework for AWS CDK in python
Home-page: https://github.com/elgamala/cdk_expects_matcher
Author: Ahmed Elgamal
Author-email: eng.ahmed.srour@gmail.com
License: MIT license
Keywords: cdk_expects_matcher
Platform: UNKNOWN
Classifier: Development Status :: 2 - Pre-Alpha
Classifier: Intended Audience :: Developers
Classifier: License :: OSI Approved :: MIT License
Classifier: Natural Language :: English
Classifier: Programming Language :: Python :: 3
Classifier: Programming Language :: Python :: 3.6
Classifier: Programming Language :: Python :: 3.7
Classifier: Programming Language :: Python :: 3.8
Requires-Python: >=3.6
